[
  {
    "id": "",
    "title": {
      "english": "The Book of the Sunnah",
      "arabic": "كتاب المقدمة"
    }
  },
  {
    "id": "1",
    "title": {
      "english": "The Book of Purification and its Sunnah",
      "arabic": "كتاب الطهارة وسننها"
    }
  },
  {
    "id": "2",
    "title": {
      "english": "The Book of the Prayer",
      "arabic": "كتاب الصلاة"
    }
  },
  {
    "id": "3",
    "title": {
      "english": "The Book of the Adhan and the Sunnah Regarding It",
      "arabic": "كتاب الأذان والسنة فيها"
    }
  },
  {
    "id": "4",
    "title": {
      "english": "The Book On The Mosques And The Congregations",
      "arabic": "كتاب المساجد والجماعات"
    }
  },
  {
    "id": "5",
    "title": {
      "english": "Establishing the Prayer and the Sunnah Regarding Them",
      "arabic": "كتاب إقامة الصلاة والسنة فيها"
    }
  },
  {
    "id": "6",
    "title": {
      "english": "Chapters Regarding Funerals",
      "arabic": "كتاب الجنائز"
    }
  },
  {
    "id": "7",
    "title": {
      "english": "Fasting",
      "arabic": "كتاب الصيام"
    }
  },
  {
    "id": "8",
    "title": {
      "english": "The Chapters Regarding Zakat",
      "arabic": "كتاب الزكاة"
    }
  },
  {
    "id": "9",
    "title": {
      "english": "The Chapters on Marriage",
      "arabic": "كتاب النكاح"
    }
  },
  {
    "id": "10",
    "title": {
      "english": "The Chapters on Divorce",
      "arabic": "كتاب الطلاق"
    }
  },
  {
    "id": "11",
    "title": {
      "english": "The Chapters on Expiation",
      "arabic": "كتاب الكفارات"
    }
  },
  {
    "id": "12",
    "title": {
      "english": "The Chapters on Business Transactions",
      "arabic": "كتاب التجارات"
    }
  },
  {
    "id": "13",
    "title": {
      "english": "The Chapters on Rulings",
      "arabic": "كتاب الأحكام"
    }
  },
  {
    "id": "14",
    "title": {
      "english": "The Chapters on Gifts",
      "arabic": "كتاب الهبات"
    }
  },
  {
    "id": "15",
    "title": {
      "english": "The Chapters on Charity",
      "arabic": "كتاب الصدقات"
    }
  },
  {
    "id": "16",
    "title": {
      "english": "The Chapters on Pawning",
      "arabic": "كتاب الرهون"
    }
  },
  {
    "id": "17",
    "title": {
      "english": "The Chapters on Pre-emption",
      "arabic": "كتاب الشفعة"
    }
  },
  {
    "id": "18",
    "title": {
      "english": "The Chapters on Lost Property",
      "arabic": "كتاب اللقطة"
    }
  },
  {
    "id": "19",
    "title": {
      "english": "The Chapters on Manumission (of Slaves)",
      "arabic": "كتاب العتق"
    }
  },
  {
    "id": "20",
    "title": {
      "english": "The Chapters on Legal Punishments",
      "arabic": "كتاب الحدود"
    }
  },
  {
    "id": "21",
    "title": {
      "english": "The Chapters on Blood Money",
      "arabic": "كتاب الديات"
    }
  },
  {
    "id": "22",
    "title": {
      "english": "The Chapters on Wills",
      "arabic": "كتاب الوصايا"
    }
  },
  {
    "id": "23",
    "title": {
      "english": "Chapters on Shares of Inheritance",
      "arabic": "كتاب الفرائض"
    }
  },
  {
    "id": "24",
    "title": {
      "english": "The Chapters on Jihad",
      "arabic": "كتاب الجهاد"
    }
  },
  {
    "id": "25",
    "title": {
      "english": "Chapters on Hajj Rituals",
      "arabic": "كتاب المناسك"
    }
  },
  {
    "id": "26",
    "title": {
      "english": "Chapters on Sacrifices",
      "arabic": "كتاب الأضاحي"
    }
  },
  {
    "id": "27",
    "title": {
      "english": "Chapters on Slaughtering",
      "arabic": "كتاب الذبائح"
    }
  },
  {
    "id": "28",
    "title": {
      "english": "Chapters on Hunting",
      "arabic": "كتاب الصيد"
    }
  },
  {
    "id": "29",
    "title": {
      "english": "Chapters on Food",
      "arabic": "كتاب الأطعمة"
    }
  },
  {
    "id": "30",
    "title": {
      "english": "Chapters on Drinks",
      "arabic": "كتاب الأشربة"
    }
  },
  {
    "id": "31",
    "title": {
      "english": "Chapters on Medicine",
      "arabic": "كتاب الطب"
    }
  },
  {
    "id": "32",
    "title": {
      "english": "Chapters on Dress",
      "arabic": "كتاب اللباس"
    }
  },
  {
    "id": "33",
    "title": {
      "english": "Etiquette",
      "arabic": "كتاب الأدب"
    }
  },
  {
    "id": "34",
    "title": {
      "english": "Supplication",
      "arabic": "كتاب الدعاء"
    }
  },
  {
    "id": "35",
    "title": {
      "english": "Interpretation of Dreams",
      "arabic": "كتاب تعبير الرؤيا"
    }
  },
  {
    "id": "36",
    "title": {
      "english": "Tribulations",
      "arabic": "كتاب الفتن"
    }
  },
  {
    "id": "37",
    "title": {
      "english": "Zuhd",
      "arabic": "كتاب الزهد"
    }
  }
]